[
	{
		"name": "Austria-Hungary",
		"leaderName": "Franz Joseph I",
		"adjective": ["Austro-Hungarian"],
		"startBias": ["Hill"],
		"preferredVictoryType": "Domination",
		
		"declaringWar": "In the name of the two crowns, you must be stopped!",
		"attacked": "Foolishness, You dare to challange our great empire?",
		"defeated": "Oh Mein Gott, All is lost!",
		"introduction": "Our glorious Empire salutes you",
		
		"neutralHello": "Hallo",
		"neutralNo": ["We absolutely refuse.","No!","I refuse."],
		"neutralYes": ["Very good.","Of course, yes.","That is very good."],

		"hateHello": "What do you want now?",
		"hateLetsHearIt": ["Speak!","What do you say?","Go on."],
		"neutralHello": "Hallo",
		"neutralNo": ["We absolutely refuse.","No!","I refuse."],
		"neutralYes": ["Very good.","Of course, yes.","That is very good."],

		"hateHello": "What do you want now?",
		"tradeRequest": "We extend a offer of trade to your nation",

		"outerColor": [197,216,109],
		"innerColor": [241,15,31],
		"uniqueName": "The Happy Apocalypse",
		"unique": ["Comment [provides a [Palace] in your first [2] cities for free (your second city also becomes a capital)]", "Provides a [Palace] in your first [2] cities for free <hidden from users>"], "[+1 Gold, +1 Happiness] in all cities connected to the capital]",
		"cities": ["Vienna","Budapest","Salzburg","Pressburg","Prague","Trieste","Szeged","Graz","Krakow",
			"Klausenburg","Lemberg","Tenesvar","Laibach","Agram","Maria-Theresiopel","Zara","Debrechen","Bozen","Pilsen",
			"Czernowitz","Kaschau","Miskolc","Sarajevo"]
	}
]
